asyncakumuli/__init__.py
asyncakumuli/_impl.py
asyncakumuli/buffered.py
asyncakumuli/collectd.py
asyncakumuli/mock.py
asyncakumuli/model.py
asyncakumuli-0.6.4.dist-info/METADATA
asyncakumuli-0.6.4.dist-info/WHEEL
asyncakumuli-0.6.4.dist-info/top_level.txt
asyncakumuli-0.6.4.dist-info/RECORD
