Metadata-Version: 2.4
Name: asyncakumuli
Version: 0.6.4
Summary: Write data to Akumuli
Author-email: Matthias Urlichs <matthias@urlichs.de>
Project-URL: homepage, http://github.com/smurfix/asyncakumuli
Keywords: iot,logging
Classifier: Operating System :: POSIX :: Linux
Classifier: Programming Language :: Python :: 3 :: Only
Classifier: Programming Language :: Python :: 3.7
Classifier: Programming Language :: Python :: 3.8
Classifier: Programming Language :: Python :: Implementation :: CPython
Classifier: Programming Language :: Python :: Implementation :: PyPy
Classifier: Framework :: Trio
Requires-Python: >=3.10
Requires-Dist: anyio>=4
Requires-Dist: httpx
Requires-Dist: pytz
